dukpyra/__init__.py
dukpyra/ast.py
dukpyra/cli.py
dukpyra/code_generator.py
dukpyra/parser.py
dukpyra/parsetab.py
dukpyra/runtime.py
dukpyra/scanner.py
dukpyra/semantic_analyzer.py
dukpyra/assets/logo.png
dukpyra/assets/mascot.png
dukpyra/templates/Program.cs.j2
dukpyra-0.3.0.dist-info/licenses/LICENSE
dukpyra-0.3.0.dist-info/METADATA
dukpyra-0.3.0.dist-info/WHEEL
dukpyra-0.3.0.dist-info/entry_points.txt
dukpyra-0.3.0.dist-info/top_level.txt
dukpyra-0.3.0.dist-info/RECORD
