Metadata-Version: 2.4
Name: dukpyra
Version: 0.3.0
Summary: Python → C# Backend Framework Compiler with Runtime Type Collection
Home-page: https://github.com/yourusername/dukpyra
Author: Dukpyra Team
Author-email: dukpyra@example.com
Project-URL: Bug Tracker, https://github.com/yourusername/dukpyra/issues
Project-URL: Documentation, https://github.com/yourusername/dukpyra
Project-URL: Source Code, https://github.com/yourusername/dukpyra
Keywords: compiler,transpiler,python,csharp,aspnet,backend,framework,research
Classifier: Development Status :: 4 - Beta
Classifier: Intended Audience :: Developers
Classifier: License :: OSI Approved :: MIT License
Classifier: Programming Language :: Python :: 3
Classifier: Programming Language :: Python :: 3.8
Classifier: Programming Language :: Python :: 3.9
Classifier: Programming Language :: Python :: 3.10
Classifier: Programming Language :: Python :: 3.11
Classifier: Programming Language :: Python :: 3.12
Classifier: Topic :: Software Development :: Compilers
Classifier: Topic :: Software Development :: Code Generators
Classifier: Framework :: FastAPI
Classifier: Typing :: Typed
Requires-Python: >=3.8
License-File: LICENSE
Requires-Dist: ply>=3.11
Requires-Dist: jinja2>=3.0.0
Requires-Dist: click>=8.0.0
Requires-Dist: fastapi>=0.100.0
Requires-Dist: uvicorn>=0.20.0
Provides-Extra: dev
Requires-Dist: pytest>=7.0.0; extra == "dev"
Requires-Dist: pytest-cov>=4.0.0; extra == "dev"
Requires-Dist: black>=23.0.0; extra == "dev"
Requires-Dist: watchdog>=3.0.0; extra == "dev"
Dynamic: author
Dynamic: author-email
Dynamic: classifier
Dynamic: description
Dynamic: description-content-type
Dynamic: home-page
Dynamic: keywords
Dynamic: license-file
Dynamic: project-url
Dynamic: provides-extra
Dynamic: requires-dist
Dynamic: requires-python
Dynamic: summary
